{"cloudnative_docker_index.md":"0ac81abc","cloudnative_k8s_index.md":"8755fee6","cloudnative_terraform_index.md":"1e4760b7","cloudnative_vmware_index.md":"cb81539d","game_poe_index.md":"89548605","index.md":"a8263b15","linux_command_index.md":"0602d523","linux_command_jjj_join.md":"a5c16238","linux_index.md":"74252727","linux_rootfs_index.md":"e964fa67","linux_service_index.md":"ff7ee5a6","network_1.md":"824d6289","powershell_index.md":"3189044e","python_base_index.md":"30c62623","python_index.md":"8279e985","python_module_index.md":"dff50c07","shell_index.md":"a7570014","vscode_index.md":"9204f805","web_css_index.md":"ace55193","web_es6_index.md":"b559e101","web_html_index.md":"cf670886","web_index.md":"c2f445d5","web_javascript_index.md":"ffe7a8d0","web_typescript_index.md":"af2288bf","web_vue3_index.md":"c319066d","windows_1.md":"4acbd825"}
