{"cloudnative_docker_index.md":"e5990f8d","cloudnative_k8s_index.md":"72694b4c","cloudnative_terraform_index.md":"34cdb383","cloudnative_vmware_index.md":"e1c0a485","game_poe_index.md":"5bf71e38","index.md":"36b6e1ea","linux_command_index.md":"7a24910a","linux_command_jjj_join.md":"998694a9","linux_index.md":"9aa6bf9e","linux_rootfs_index.md":"43255a9d","linux_service_index.md":"ad68fd10","network_1.md":"f7486ca9","powershell_index.md":"9072804b","python_base_index.md":"acf9a5c7","python_index.md":"97727056","python_module_index.md":"c68e87ca","shell_index.md":"03722348","vscode_index.md":"d4aa60d6","web_css_index.md":"00deb867","web_es6_index.md":"8d5d5c6a","web_html_index.md":"cef76845","web_index.md":"9ce7b52f","web_javascript_index.md":"a792ecf9","web_typescript_index.md":"4443461b","web_vue3_index.md":"5907adc7","windows_1.md":"40c4c671"}
